{"id":"b05768e1-e1ba-4244-b733-b2ab0809d810","revision":0,"last_node_id":103,"last_link_id":184,"nodes":[{"id":103,"type":"bbc1bd7f-4cf5-4cc0-85b1-0cf65c50939e","pos":[3205.199399841747,1930.2264440082595],"size":[210,258],"flags":{},"order":0,"mode":0,"inputs":[{"localized_name":"image","name":"image","type":"IMAGE","link":null},{"name":"text","type":"STRING","widget":{"name":"text"},"link":null},{"name":"text_1","type":"STRING","widget":{"name":"text_1"},"link":null},{"name":"steps","type":"INT","widget":{"name":"steps"},"link":null},{"name":"cfg","type":"FLOAT","widget":{"name":"cfg"},"link":null},{"name":"sampler_name","type":"COMBO","widget":{"name":"sampler_name"},"link":null},{"name":"denoise","type":"FLOAT","widget":{"name":"denoise"},"link":null}],"outputs":[{"localized_name":"IMAGE","name":"IMAGE","type":"IMAGE","links":[]}],"properties":{"proxyWidgets":[["86","text"],["12","text"],["-1","steps"],["-1","cfg"],["-1","sampler_name"],["-1","denoise"],["85","seed"]],"cnr_id":"comfy-core","ver":"0.6.0","ue_properties":{"widget_ue_connectable":{},"input_ue_unconnectable":{},"version":"7.5.2"}},"widgets_values":[null,null,2,3,"uni_pc",0.25]}],"links":[],"groups":[],"definitions":{"subgraphs":[{"id":"bbc1bd7f-4cf5-4cc0-85b1-0cf65c50939e","version":1,"state":{"lastGroupId":3,"lastNodeId":102,"lastLinkId":186,"lastRerouteId":0},"revision":0,"config":{},"name":"Upscaler","inputNode":{"id":-10,"bounding":[2153.0445543451906,1898.2264440082595,122.564453125,140]},"outputNode":{"id":-20,"bounding":[4277.354245338303,1898.2264440082595,120,60]},"inputs":[{"id":"928ce795-d78b-4efb-a7bf-fe9e40d7c608","name":"image","type":"IMAGE","linkIds":[149,148],"localized_name":"image","pos":[2255.6090074701906,1918.2264440082595]},{"id":"d4ed7d06-7b28-49ab-9949-a2adcab32c39","name":"steps","type":"INT","linkIds":[183],"pos":[2255.6090074701906,1938.2264440082595]},{"id":"40b47b73-4e03-41e2-a2ac-48e38da48bc6","name":"cfg","type":"FLOAT","linkIds":[184],"pos":[2255.6090074701906,1958.2264440082595]},{"id":"b9011e65-9c44-4770-914e-0a7ac7313824","name":"sampler_name","type":"COMBO","linkIds":[185],"pos":[2255.6090074701906,1978.2264440082595]},{"id":"d6ccd956-bd36-4c4c-9578-5c76b7ddeedc","name":"denoise","type":"FLOAT","linkIds":[186],"pos":[2255.6090074701906,1998.2264440082595]}],"outputs":[{"id":"76cb7a14-794e-4248-b97c-e2c5b65c8075","name":"IMAGE","type":"IMAGE","linkIds":[150],"localized_name":"IMAGE","pos":[4297.354245338303,1918.2264440082595]}],"widgets":[],"nodes":[{"id":74,"type":"ImageFromBatch","pos":[2503.2797438877396,2098.1059022332747],"size":[270,82],"flags":{},"order":9,"mode":4,"inputs":[{"localized_name":"image","name":"image","type":"IMAGE","link":149},{"localized_name":"batch_index","name":"batch_index","type":"INT","widget":{"name":"batch_index"},"link":null},{"localized_name":"length","name":"length","type":"INT","widget":{"name":"length"},"link":null}],"outputs":[{"localized_name":"IMAGE","name":"IMAGE","type":"IMAGE","links":[120]}],"properties":{"cnr_id":"comfy-core","ver":"0.3.59","Node name for S&R":"ImageFromBatch","ue_properties":{"widget_ue_connectable":{},"version":"7.2.2","input_ue_unconnectable":{}},"enableTabs":false,"tabWidth":65,"tabXOffset":10,"hasSecondTab":false,"secondTabText":"Send Back","secondTabOffset":80,"secondTabWidth":65},"widgets_values":[0,1]},{"id":63,"type":"easy imageInterrogator","pos":[2793.2797438877396,2098.1059022332747],"size":[280,82],"flags":{},"order":6,"mode":4,"inputs":[{"localized_name":"image","name":"image","type":"IMAGE","link":120},{"localized_name":"mode","name":"mode","type":"COMBO","widget":{"name":"mode"},"link":null},{"localized_name":"use_lowvram","name":"use_lowvram","type":"BOOLEAN","widget":{"name":"use_lowvram"},"link":null}],"outputs":[{"localized_name":"prompt","name":"prompt","shape":6,"type":"STRING","links":[126]}],"properties":{"cnr_id":"comfyui-easy-use","ver":"1.3.3","Node name for S&R":"easy imageInterrogator","ue_properties":{"widget_ue_connectable":{},"version":"7.2.2","input_ue_unconnectable":{}},"enableTabs":false,"tabWidth":65,"tabXOffset":10,"hasSecondTab":false,"secondTabText":"Send Back","secondTabOffset":80,"secondTabWidth":65},"widgets_values":["fast",true]},{"id":79,"type":"easy showAnything","pos":[3108.0370681064896,2098.5040955926497],"size":[333.5094299316406,169.27935791015625],"flags":{},"order":10,"mode":4,"inputs":[{"localized_name":"anything","name":"anything","shape":7,"type":"*","link":126}],"outputs":[{"localized_name":"output","name":"output","type":"*","links":null}],"properties":{"cnr_id":"comfyui-easy-use","ver":"1.3.3","Node name for S&R":"easy showAnything","ue_properties":{"widget_ue_connectable":{},"version":"7.5.2","input_ue_unconnectable":{}}},"widgets_values":[]},{"id":86,"type":"CLIPTextEncode","pos":[3003.003662109375,1761.904296875],"size":[371.9207458496094,142.02947998046875],"flags":{},"order":5,"mode":0,"inputs":[{"localized_name":"clip","name":"clip","type":"CLIP","link":180},{"localized_name":"text","name":"text","type":"STRING","widget":{"name":"text"},"link":null}],"outputs":[{"localized_name":"CONDITIONING","name":"CONDITIONING","type":"CONDITIONING","links":[142]}],"title":"Negative Prompt","properties":{"cnr_id":"comfy-core","ver":"0.3.64","Node name for S&R":"CLIPTextEncode","ue_properties":{"widget_ue_connectable":{"text":true},"version":"7.5.2","input_ue_unconnectable":{}}},"widgets_values":[""],"color":"#322","bgcolor":"#533"},{"id":12,"type":"CLIPTextEncode","pos":[3004.703369140625,1546.3702392578125],"size":[370,160],"flags":{"collapsed":false},"order":4,"mode":0,"inputs":[{"localized_name":"clip","name":"clip","type":"CLIP","link":179},{"localized_name":"text","name":"text","type":"STRING","widget":{"name":"text"},"link":null}],"outputs":[{"localized_name":"CONDITIONING","name":"CONDITIONING","type":"CONDITIONING","links":[137]}],"title":"Positive Prompt","properties":{"cnr_id":"comfy-core","ver":"0.3.43","Node name for S&R":"CLIPTextEncode","ue_properties":{"version":"7.0.1","widget_ue_connectable":{}},"enableTabs":false,"tabWidth":65,"tabXOffset":10,"hasSecondTab":false,"secondTabText":"Send Back","secondTabOffset":80,"secondTabWidth":65},"widgets_values":[""],"color":"#232","bgcolor":"#353"},{"id":73,"type":"Reroute","pos":[3433.22632822969,1270.524431774481],"size":[75,26],"flags":{},"order":8,"mode":0,"inputs":[{"name":"","type":"*","link":160}],"outputs":[{"name":"","type":"IMAGE","links":[135]}],"properties":{"showOutputText":false,"horizontal":false,"ue_properties":{"widget_ue_connectable":{},"version":"7.2.2","input_ue_unconnectable":{}}}},{"id":70,"type":"ImageUpscaleWithModel","pos":[2685.5919119312043,1256.8018256613311],"size":[310,46],"flags":{},"order":7,"mode":0,"inputs":[{"localized_name":"upscale_model","name":"upscale_model","type":"UPSCALE_MODEL","link":111},{"localized_name":"image","name":"image","type":"IMAGE","link":148}],"outputs":[{"localized_name":"IMAGE","name":"IMAGE","type":"IMAGE","links":[159]}],"properties":{"cnr_id":"comfy-core","ver":"0.3.59","Node name for S&R":"ImageUpscaleWithModel","ue_properties":{"widget_ue_connectable":{},"version":"7.2.2","input_ue_unconnectable":{}},"enableTabs":false,"tabWidth":65,"tabXOffset":10,"hasSecondTab":false,"secondTabText":"Send Back","secondTabOffset":80,"secondTabWidth":65},"widgets_values":[]},{"id":102,"type":"Label (rgthree)","pos":[3789.365964088303,1189.7798009875455],"size":[417.98828125,40],"flags":{"allow_interaction":true},"order":0,"mode":0,"inputs":[],"outputs":[],"title":"Adust Sampler Settings","properties":{"fontSize":40,"fontFamily":"Arial","fontColor":"#ffffff","textAlign":"left","backgroundColor":"transparent","padding":0,"borderRadius":0,"angle":0,"ue_properties":{"widget_ue_connectable":{},"version":"7.5.2","input_ue_unconnectable":{}}},"color":"#fff0","bgcolor":"#fff0"},{"id":100,"type":"CheckpointLoaderSimple","pos":[2703.1970579378053,988.7358056762196],"size":[270,98],"flags":{},"order":1,"mode":0,"inputs":[{"localized_name":"ckpt_name","name":"ckpt_name","type":"COMBO","widget":{"name":"ckpt_name"},"link":null}],"outputs":[{"localized_name":"MODEL","name":"MODEL","type":"MODEL","links":[182]},{"localized_name":"CLIP","name":"CLIP","type":"CLIP","links":[179,180]},{"localized_name":"VAE","name":"VAE","type":"VAE","links":[181]}],"properties":{"cnr_id":"comfy-core","ver":"0.3.65","Node name for S&R":"CheckpointLoaderSimple","ue_properties":{"widget_ue_connectable":{"ckpt_name":true},"version":"7.5.2","input_ue_unconnectable":{}}},"widgets_values":["waiNSFWIllustrious_v110.safetensors"]},{"id":69,"type":"UpscaleModelLoader","pos":[2351.585213961648,1253.1405775325322],"size":[300,60],"flags":{},"order":2,"mode":0,"inputs":[{"localized_name":"model_name","name":"model_name","type":"COMBO","widget":{"name":"model_name"},"link":null}],"outputs":[{"localized_name":"UPSCALE_MODEL","name":"UPSCALE_MODEL","type":"UPSCALE_MODEL","links":[111]}],"properties":{"cnr_id":"comfy-core","ver":"0.3.59","Node name for S&R":"UpscaleModelLoader","ue_properties":{"widget_ue_connectable":{},"version":"7.2.2","input_ue_unconnectable":{}},"enableTabs":false,"tabWidth":65,"tabXOffset":10,"hasSecondTab":false,"secondTabText":"Send Back","secondTabOffset":80,"secondTabWidth":65},"widgets_values":["4x_fatal_Anime_500000_G.pth"]},{"id":101,"type":"Note","pos":[2562.163401783911,2421.3558985771774],"size":[885.1842794693016,509.9611837631222],"flags":{},"order":3,"mode":0,"inputs":[],"outputs":[],"title":"Models","properties":{"ue_properties":{"widget_ue_connectable":{},"version":"7.1","input_ue_unconnectable":{}}},"widgets_values":["Required models for Image Latent Upscale (SDXL) Workflow:\n\nSDXL Juggernaut: https://civitai.com/models/133005/juggernaut-xl\nUpscalers: https://huggingface.co/uwg/upscaler/tree/main/ESRGAN\n\n\nFile save location\n\nComfyUI/\n├───📂 models/\n│   ├───📂 checkpoints/\n│   │   ├─── juggernautXL_ragnarokBy.safetensors\n│   ├───📂 upscale_models/\n│   │   ├─── 4x_NMKD-Siax_200k.pth\n│   │   ├─── 4x-AnimeSharp.pth\n│   │   ├─── 4x-UltraSharp\n\n\n\n\n\n"],"color":"#432","bgcolor":"#653"},{"id":92,"type":"ImageScaleBy","pos":[3064.028851705496,1257.4099603153907],"size":[270,82],"flags":{},"order":12,"mode":0,"inputs":[{"localized_name":"image","name":"image","type":"IMAGE","link":159},{"localized_name":"upscale_method","name":"upscale_method","type":"COMBO","widget":{"name":"upscale_method"},"link":null},{"localized_name":"scale_by","name":"scale_by","type":"FLOAT","widget":{"name":"scale_by"},"link":null}],"outputs":[{"localized_name":"IMAGE","name":"IMAGE","type":"IMAGE","links":[160]}],"properties":{"cnr_id":"comfy-core","ver":"0.3.65","Node name for S&R":"ImageScaleBy","ue_properties":{"widget_ue_connectable":{"upscale_method":true,"scale_by":true},"version":"7.5.2","input_ue_unconnectable":{}}},"widgets_values":["lanczos",0.5]},{"id":85,"type":"UltimateSDUpscaleNoUpscale","pos":[3835.407470703125,1348.6962890625],"size":[314.6304626464844,1104.5137939453125],"flags":{},"order":11,"mode":0,"inputs":[{"localized_name":"upscaled_image","name":"upscaled_image","type":"IMAGE","link":135},{"localized_name":"model","name":"model","type":"MODEL","link":182},{"localized_name":"positive","name":"positive","type":"CONDITIONING","link":137},{"localized_name":"negative","name":"negative","type":"CONDITIONING","link":142},{"localized_name":"vae","name":"vae","type":"VAE","link":181},{"localized_name":"seed","name":"seed","type":"INT","widget":{"name":"seed"},"link":null},{"localized_name":"steps","name":"steps","type":"INT","widget":{"name":"steps"},"link":183},{"localized_name":"cfg","name":"cfg","type":"FLOAT","widget":{"name":"cfg"},"link":184},{"localized_name":"sampler_name","name":"sampler_name","type":"COMBO","widget":{"name":"sampler_name"},"link":185},{"localized_name":"scheduler","name":"scheduler","type":"COMBO","widget":{"name":"scheduler"},"link":null},{"localized_name":"denoise","name":"denoise","type":"FLOAT","widget":{"name":"denoise"},"link":186},{"localized_name":"mode_type","name":"mode_type","type":"COMBO","widget":{"name":"mode_type"},"link":null},{"localized_name":"tile_width","name":"tile_width","type":"INT","widget":{"name":"tile_width"},"link":null},{"localized_name":"tile_height","name":"tile_height","type":"INT","widget":{"name":"tile_height"},"link":null},{"localized_name":"mask_blur","name":"mask_blur","type":"INT","widget":{"name":"mask_blur"},"link":null},{"localized_name":"tile_padding","name":"tile_padding","type":"INT","widget":{"name":"tile_padding"},"link":null},{"localized_name":"seam_fix_mode","name":"seam_fix_mode","type":"COMBO","widget":{"name":"seam_fix_mode"},"link":null},{"localized_name":"seam_fix_denoise","name":"seam_fix_denoise","type":"FLOAT","widget":{"name":"seam_fix_denoise"},"link":null},{"localized_name":"seam_fix_width","name":"seam_fix_width","type":"INT","widget":{"name":"seam_fix_width"},"link":null},{"localized_name":"seam_fix_mask_blur","name":"seam_fix_mask_blur","type":"INT","widget":{"name":"seam_fix_mask_blur"},"link":null},{"localized_name":"seam_fix_padding","name":"seam_fix_padding","type":"INT","widget":{"name":"seam_fix_padding"},"link":null},{"localized_name":"force_uniform_tiles","name":"force_uniform_tiles","type":"BOOLEAN","widget":{"name":"force_uniform_tiles"},"link":null},{"localized_name":"tiled_decode","name":"tiled_decode","type":"BOOLEAN","widget":{"name":"tiled_decode"},"link":null}],"outputs":[{"localized_name":"IMAGE","name":"IMAGE","type":"IMAGE","links":[150]}],"properties":{"cnr_id":"comfyui_ultimatesdupscale","ver":"871c7cb134797f6ed68e323090532f77110194a7","Node name for S&R":"UltimateSDUpscaleNoUpscale","ue_properties":{"widget_ue_connectable":{"seed":true,"steps":true,"cfg":true,"sampler_name":true,"scheduler":true,"denoise":true,"mode_type":true,"tile_width":true,"tile_height":true,"mask_blur":true,"tile_padding":true,"seam_fix_mode":true,"seam_fix_denoise":true,"seam_fix_width":true,"seam_fix_mask_blur":true,"seam_fix_padding":true,"force_uniform_tiles":true,"tiled_decode":true},"version":"7.5.2","input_ue_unconnectable":{}}},"widgets_values":[909019960945989,"randomize",2,3,"uni_pc","normal",0.25,"Chess",1024,1024,8,32,"None",1,64,8,16,true,false]}],"groups":[{"id":3,"title":"Upscaler","bounding":[2333.0445543451906,915.1358056762195,1884.3096909931128,2026.18127666408],"color":"#3f789e","font_size":24,"flags":{}},{"id":1,"title":"Optional Upscale","bounding":[2343.0445543451906,1184.0931537029435,1011.6317508087213,198.35399186809968],"color":"#3f789e","font_size":24,"flags":{}},{"id":2,"title":"Prompt Generator","bounding":[2483.2797438877396,2008.1078553582752,1000,280],"color":"#3f789e","font_size":24,"flags":{}}],"links":[{"id":120,"origin_id":74,"origin_slot":0,"target_id":63,"target_slot":0,"type":"IMAGE"},{"id":126,"origin_id":63,"origin_slot":0,"target_id":79,"target_slot":0,"type":"*"},{"id":180,"origin_id":100,"origin_slot":1,"target_id":86,"target_slot":0,"type":"CLIP"},{"id":179,"origin_id":100,"origin_slot":1,"target_id":12,"target_slot":0,"type":"CLIP"},{"id":160,"origin_id":92,"origin_slot":0,"target_id":73,"target_slot":0,"type":"*"},{"id":111,"origin_id":69,"origin_slot":0,"target_id":70,"target_slot":0,"type":"UPSCALE_MODEL"},{"id":159,"origin_id":70,"origin_slot":0,"target_id":92,"target_slot":0,"type":"IMAGE"},{"id":135,"origin_id":73,"origin_slot":0,"target_id":85,"target_slot":0,"type":"IMAGE"},{"id":182,"origin_id":100,"origin_slot":0,"target_id":85,"target_slot":1,"type":"MODEL"},{"id":137,"origin_id":12,"origin_slot":0,"target_id":85,"target_slot":2,"type":"CONDITIONING"},{"id":142,"origin_id":86,"origin_slot":0,"target_id":85,"target_slot":3,"type":"CONDITIONING"},{"id":181,"origin_id":100,"origin_slot":2,"target_id":85,"target_slot":4,"type":"VAE"},{"id":149,"origin_id":-10,"origin_slot":0,"target_id":74,"target_slot":0,"type":"IMAGE"},{"id":148,"origin_id":-10,"origin_slot":0,"target_id":70,"target_slot":1,"type":"IMAGE"},{"id":150,"origin_id":85,"origin_slot":0,"target_id":-20,"target_slot":0,"type":"IMAGE"},{"id":183,"origin_id":-10,"origin_slot":1,"target_id":85,"target_slot":6,"type":"INT"},{"id":184,"origin_id":-10,"origin_slot":2,"target_id":85,"target_slot":7,"type":"FLOAT"},{"id":185,"origin_id":-10,"origin_slot":3,"target_id":85,"target_slot":8,"type":"COMBO"},{"id":186,"origin_id":-10,"origin_slot":4,"target_id":85,"target_slot":10,"type":"FLOAT"}],"extra":{"workflowRendererVersion":"LG","ue_links":[]}}]},"config":{},"extra":{"frontendVersion":"1.25.11","VHS_latentpreview":false,"VHS_latentpreviewrate":0,"VHS_MetadataImage":true,"VHS_KeepIntermediate":true,"ue_links":[],"links_added_by_ue":[],"workflowRendererVersion":"LG"},"version":0.4}